icu_benchmarks/__init__.py
icu_benchmarks/contants.py
icu_benchmarks/cross_validation.py
icu_benchmarks/run.py
icu_benchmarks/run_utils.py
icu_benchmarks/wandb_utils.py
yaib-0.3.1.dist-info/LICENSE
yaib-0.3.1.dist-info/METADATA
yaib-0.3.1.dist-info/WHEEL
yaib-0.3.1.dist-info/entry_points.txt
yaib-0.3.1.dist-info/top_level.txt
yaib-0.3.1.dist-info/RECORD
