Metadata-Version: 2.1
Name: yaib
Version: 0.3.1
Summary: Yet Another ICU Benchmark is a holistic framework for the automation of the development of clinical prediction models on ICU data. Users can create custom datasets, cohorts, prediction tasks, endpoints, and models. 
Home-page: https://github.com/rvandewater/YAIB
Author: Robin van de Water
Author-email: robin.vandewater@hpi.de
License: MIT license
Keywords: benchmark mimic-iii eicu hirid clinical-ml machine-learning benchmark time-series mimic-iv patient-monitoring amsterdamumcdb clinical-data ehr icu ricu pyicu
Classifier: Development Status :: 4 - Beta
Classifier: Intended Audience :: Developers
Classifier: License :: OSI Approved :: MIT License
Classifier: Natural Language :: English
Classifier: Programming Language :: Python :: 3.10
License-File: LICENSE
Requires-Dist: black (==23.3.0)
Requires-Dist: coverage (==7.2.3)
Requires-Dist: flake8 (==5.0.4)
Requires-Dist: matplotlib (==3.7.1)
Requires-Dist: gin-config (==0.5.0)
Requires-Dist: pytorch-ignite (==0.4.11)
Requires-Dist: torch (==2.0.1)
Requires-Dist: pytorch-cuda (==11.8)
Requires-Dist: lightgbm (==3.3.5)
Requires-Dist: numpy (==1.24.3)
Requires-Dist: pandas (==2.0.0)
Requires-Dist: pyarrow (==11.0.0)
Requires-Dist: pytest (==7.3.1)
Requires-Dist: scikit-learn (==1.2.2)
Requires-Dist: tensorboard (==2.12.2)
Requires-Dist: tqdm (==4.64.1)
Requires-Dist: pytorch-lightning (==2.0.3)
Requires-Dist: wandb (==0.15.4)
Requires-Dist: pip (==23.1)
Requires-Dist: einops (==0.6.1)
Requires-Dist: hydra-core (==1.3)
Requires-Dist: recipies (==0.1.1)
Provides-Extra: mps
Requires-Dist: mkl (<2022) ; extra == 'mps'
